jsonblob/__init__.py
jsonblob/jsonblob.py
jsonblob-0.0.2.dist-info/licenses/LICENCE.txt
jsonblob-0.0.2.dist-info/METADATA
jsonblob-0.0.2.dist-info/WHEEL
jsonblob-0.0.2.dist-info/top_level.txt
jsonblob-0.0.2.dist-info/RECORD
