Metadata-Version: 2.4
Name: jsonblob
Version: 0.0.2
Summary: Non official jsonblob api client
Author-email: Roman Smolnyk <poma23324@gmail.com>
Project-URL: Homepage, https://github.com/roman-smolnyk/python-jsonblob
Keywords: jsonblob
Classifier: Programming Language :: Python :: 3
Classifier: License :: OSI Approved :: MIT License
Classifier: Operating System :: OS Independent
Requires-Python: >=3.8
License-File: LICENCE.txt
Requires-Dist: requests
Dynamic: license-file
